{
 "updated": "2026-06-26 13:58",
 "stocks": [
  {
   "code": "000720",
   "name": "현대건설",
   "score": 96.5,
   "reason": "금융투자 매집 · 메릴린치 · 2일 · 보유원가 127.3억 · 평단 113,750원 (일치 96%)"
  },
  {
   "code": "451250",
   "name": "삐아",
   "score": 100.0,
   "reason": "금융투자 매집 · 신  영 · 2일 · 보유원가 4.6억 · 평단 7,610원 (일치 100%)"
  },
  {
   "code": "214320",
   "name": "이노션",
   "score": 99.5,
   "reason": "사모펀드 매집 · NH투자증권 · 2일 · 보유원가 4.0억 · 평단 18,184원 (일치 100%)"
  },
  {
   "code": "264900",
   "name": "크라운제과",
   "score": 96.3,
   "reason": "사모펀드 매집 · 한국투자증권 · 2일 · 보유원가 3.6억 · 평단 7,747원 (일치 96%)"
  },
  {
   "code": "001530",
   "name": "DI동일",
   "score": 98.1,
   "reason": "사모펀드 매집 · KB증권 · 2일 · 보유원가 3.4억 · 평단 21,780원 (일치 98%)"
  },
  {
   "code": "065510",
   "name": "휴비츠",
   "score": 98.9,
   "reason": "금융투자 매집 · 대  신 · 2일 · 보유원가 3.3억 · 평단 6,849원 (일치 99%)"
  },
  {
   "code": "000430",
   "name": "대원강업",
   "score": 95.6,
   "reason": "기타법인 매집 · 한  화 · 2일 · 보유원가 2.9억 · 평단 3,894원 (일치 96%)"
  },
  {
   "code": "060260",
   "name": "뉴보텍",
   "score": 98.9,
   "reason": "금융투자 매집 · SK증권 · 2일 · 보유원가 2.7억 · 평단 1,403원 (일치 99%)"
  },
  {
   "code": "057540",
   "name": "옴니시스템",
   "score": 98.0,
   "reason": "기타법인 매집 · 대  신 · 2일 · 보유원가 2.3억 · 평단 809원 (일치 98%)"
  },
  {
   "code": "053160",
   "name": "프리엠스",
   "score": 98.7,
   "reason": "기타법인 매집 · KB증권 · 2일 · 보유원가 2.2억 · 평단 9,351원 (일치 99%)"
  },
  {
   "code": "148930",
   "name": "에이치와이티씨",
   "score": 99.4,
   "reason": "금융투자 매집 · 신  영 · 2일 · 보유원가 1.8억 · 평단 2,944원 (일치 99%)"
  },
  {
   "code": "020400",
   "name": "대동금속",
   "score": 99.2,
   "reason": "금융투자 매집 · 삼  성 · 2일 · 보유원가 1.5억 · 평단 3,149원 (일치 99%)"
  },
  {
   "code": "348030",
   "name": "모비릭스",
   "score": 97.8,
   "reason": "금융투자 매집 · 유안타 · 2일 · 보유원가 1.4억 · 평단 2,377원 (일치 98%)"
  },
  {
   "code": "432980",
   "name": "엠에프씨",
   "score": 98.1,
   "reason": "기타법인 매집 · 하나증권 · 2일 · 보유원가 1.2억 · 평단 2,963원 (일치 98%)"
  },
  {
   "code": "038540",
   "name": "상상인",
   "score": 97.8,
   "reason": "금융투자 매집 · NH투자증권 · 2일 · 보유원가 1.1억 · 평단 2,010원 (일치 98%)"
  },
  {
   "code": "332370",
   "name": "아이디피",
   "score": 98.3,
   "reason": "기타법인 매집 · 유진투자증권 · 2일 · 보유원가 1.0억 · 평단 5,109원 (일치 98%)"
  }
 ]
}